balanced_clustering/__init__.py
balanced_clustering/ami.py
balanced_clustering/ari.py
balanced_clustering/utils/__init__.py
balanced_clustering/utils/_emi_cython.pyx
balanced_clustering/utils/avg.py
balanced_clustering/utils/checks.py
balanced_clustering/utils/contingency.py
balanced_clustering/utils/mi.py
balanced_clustering/vmeasure.py
balanced_clustering-0.1.0.dist-info/LICENSE.md
balanced_clustering-0.1.0.dist-info/WHEEL
balanced_clustering-0.1.0.dist-info/METADATA
balanced_clustering-0.1.0.dist-info/RECORD
